{
    "dynamic":  true,
    "protectedPhases":  "1-81 protected after validation",
    "protectedSystems":  {
                             "secretsUntouched":  true,
                             "collectionsUntouched":  true,
                             "paymentsUntouched":  true,
                             "oauthUntouched":  true,
                             "productsUntouched":  true
                         },
    "phase":  "81",
    "title":  "Brian \u0026 Co Phase 81 Dynamic Protection Registry",
    "status":  "prepared"
}
